rena_odd_even/__init__.py
rena_odd_even/core.py
rena_odd_even-0.1.0.dist-info/licenses/LICENCE
rena_odd_even-0.1.0.dist-info/METADATA
rena_odd_even-0.1.0.dist-info/WHEEL
rena_odd_even-0.1.0.dist-info/top_level.txt
rena_odd_even-0.1.0.dist-info/RECORD
